{
  "items": [
    {
      "id": "q_retry_demo",
      "message": "[OpenClaw测试] 重试队列发送测试，可忽略。",
      "target": "+447354918289",
      "source": "test",
      "attempts": 3,
      "maxAttempts": 3,
      "status": "failed",
      "created": "2026-03-17T22:20",
      "lastReason": "GatewayClientRequestError: Error: No active WhatsApp Web listener (account: default). Start the gateway, then link WhatsApp with: openclaw channels login --chan"
    },
    {
      "id": "q_20260317_230002_076998",
      "message": "小磊哥，我识别到你的命令：设置明天早上7点20的闹钟 `优先级：高` `截止：2025-04-06`\n**备注**\n语音中“明年”应为口误，实际指“明天”（常规语音识别纠错），按当前日期2025年4月5日推算，闹钟时间为2025年4月6日7:20。。但信息还不完整（rejected_by_semantic_gate）。请回复：小熊同学 回复 q_20260317_230002_076403: <补充内容>",
      "target": "+447354918289",
      "source": "question",
      "attempts": 0,
      "maxAttempts": 3,
      "status": "pending",
      "created": "2026-03-17T23:00",
      "lastReason": "precheck_not_connected:precheck_error:[Errno 2] No such file or directory: 'openclaw'"
    },
    {
      "id": "q_20260317_231501_421020",
      "message": "小磊哥，我识别到你的命令：”为唤醒指令对象，非任务执行人。。但信息还不完整（rejected_by_semantic_gate）。请回复：小熊同学 回复 q_20260317_231501_420391: <补充内容>",
      "target": "+447354918289",
      "source": "question",
      "attempts": 0,
      "maxAttempts": 3,
      "status": "pending",
      "created": "2026-03-17T23:15",
      "lastReason": "precheck_not_connected:precheck_error:[Errno 2] No such file or directory: 'openclaw'"
    },
    {
      "id": "q_20260317_233001_804053",
      "message": "小磊哥，我识别到你的命令：设置明天早上7点20的闹钟 `优先级：高` `截止：2025-04-06`\n**备注**\n语音中“明年”应为口误，实际指“明天”（常规语音识别纠错），按当前日期2025年4月5日推算，闹钟时间为2025年4月6日7:20。。但信息还不完整（rejected_by_semantic_gate）。请回复：小熊同学 回复 q_20260317_233001_803410: <补充内容>",
      "target": "+447354918289",
      "source": "question",
      "attempts": 0,
      "maxAttempts": 3,
      "status": "pending",
      "created": "2026-03-17T23:30",
      "lastReason": "precheck_not_connected:precheck_error:[Errno 2] No such file or directory: 'openclaw'"
    },
    {
      "id": "q_20260317_233001_853043",
      "message": "小磊哥，我识别到你的命令：”为唤醒指令对象，非任务执行人。。但信息还不完整（rejected_by_semantic_gate）。请回复：小熊同学 回复 q_20260317_233001_852492: <补充内容>",
      "target": "+447354918289",
      "source": "question",
      "attempts": 0,
      "maxAttempts": 3,
      "status": "pending",
      "created": "2026-03-17T23:30",
      "lastReason": "precheck_not_connected:precheck_error:[Errno 2] No such file or directory: 'openclaw'"
    },
    {
      "id": "q_20260317_233001_902635",
      "message": "小磊哥，我识别到你的命令：执行 `优先级：高` `截止：YYYY-MM-DD`\n**备注**\n语音内容共14字，未达15字，仅输出核心任务项，不扩写；“明天”需动态解析为具体日期（如今天是2024-06-15，则截止为2024-06-16）；“小熊同学”为指定执行人，非泛指。。但信息还不完整（rejected_by_semantic_gate）。请回复：小熊同学 回复 q_20260317_233001_902084: <补充内容>",
      "target": "+447354918289",
      "source": "question",
      "attempts": 0,
      "maxAttempts": 3,
      "status": "pending",
      "created": "2026-03-17T23:30",
      "lastReason": "precheck_not_connected:precheck_error:[Errno 2] No such file or directory: 'openclaw'"
    },
    {
      "id": "q_20260317_233502_051120",
      "message": "小磊哥，我识别到你的命令：设置明天早上7:30的闹钟 `优先级：高` `截止：2024-06-15`\n**备注**\n语音内容仅含单一明确指令，无复杂任务需拆解；截止时间为“明天”，按当前日期2024-06-14推算为2024-06-15。。但信息还不完整（rejected_by_semantic_gate）。请回复：小熊同学 回复 q_20260317_233502_050470: <补充内容>",
      "target": "+447354918289",
      "source": "question",
      "attempts": 0,
      "maxAttempts": 3,
      "status": "pending",
      "created": "2026-03-17T23:35",
      "lastReason": "precheck_not_connected:precheck_error:[Errno 2] No such file or directory: 'openclaw'"
    }
  ]
}